MANIFEST.in
README.md
setup.py
li_rn_networks/f_pfc_unit.py
li_rn_networks/function.py
li_rn_networks/functions.py
li_rn_networks/li_rn_network.py
li_rn_networks/non_layer_unit.py
li_rn_networks/non_neuron.py
li_rn_networks/optimizer.py
li_rn_networks/pi_gen_imput_data.py
li_rn_networks/rnn_layer_unit.py
li_rn_networks/rnn_neuron.py
li_rn_networks/rnnclass.py
li_rn_networks/test_rnn_realtime.py
li_rn_networks/traning.py
li_rn_networks.egg-info/PKG-INFO
li_rn_networks.egg-info/SOURCES.txt
li_rn_networks.egg-info/dependency_links.txt
li_rn_networks.egg-info/top_level.txt