Metadata-Version: 2.1
Name: li_rn_networks
Version: 0.1
Summary: neural networks. It have recurrent connections and leaky integrator neuron.
Home-page: https://github.com/shibuiwilliam/py-kaomoji.git
Author: picker.
Author-email: picker@pickerlav.jp
License: UNKNOWN
Platform: UNKNOWN
